reporter/__init__.py
reporter/__main__.py
reporter/main.py
report_by_csv_cu_homework-0.1.0.dist-info/METADATA
report_by_csv_cu_homework-0.1.0.dist-info/WHEEL
report_by_csv_cu_homework-0.1.0.dist-info/top_level.txt
report_by_csv_cu_homework-0.1.0.dist-info/RECORD
